anki_card_create/__init__.py
anki_card_create/exceptions.py
anki_card_create/card_creator/__init__.py
anki_card_create/card_creator/card_creator.py
anki_card_create/cli/__init__.py
anki_card_create/cli/main.py
anki_card_create/config/__init__.py
anki_card_create/config/settings.py
anki_card_create/models/__init__.py
anki_card_create/models/anki_note.py
anki_card_create/models/kanki_input.py
anki_card_create/models/response.py
anki_card_create/models/translator_input.py
anki_card_create/services/__init__.py
anki_card_create/services/ai_agent_services.py
anki_card_create/services/anki_client.py
anki_card_create/services/translators.py
anki_card_create/services/utils.py
anki_card_create-0.2.1.dist-info/METADATA
anki_card_create-0.2.1.dist-info/WHEEL
anki_card_create-0.2.1.dist-info/entry_points.txt
anki_card_create-0.2.1.dist-info/RECORD
