Metadata-Version: 2.4
Name: anki_card_create
Version: 0.2.1
Project-URL: homepage, https://github.com/phlin0424/anki-card-create
Project-URL: repository, https://github.com/phlin0424/anki-card-create
Requires-Python: >=3.11
Requires-Dist: deep-translator>=1.11.4
Requires-Dist: langdetect>=1.0.9
Requires-Dist: navertts>=0.3.1
Requires-Dist: pydantic-ai>=0.0.44
Requires-Dist: pydantic-settings>=2.3.4
Requires-Dist: pydantic>=2.6.4
Requires-Dist: requests>=2.31.0
